{
  "named": {
    "70": "DOANE",
    "104": "STEPHANOS",
    "105": "BULLINGER",
    "106": "BOOTH",
    "108": "OLIVET",
    "111": "FEDERAL STREET",
    "112": "HARTEL",
    "113": "WELTON",
    "114": "BACA",
    "115": "OSCAR",
    "116": "WEBB",
    "117": "AURELIA",
    "118": "ST. HILDA",
    "119": "ST. LEONARD",
    "120": "PERSEVERANCE",
    "121": "LANGRAN",
    "122": "PERSEVERANCE",
    "123": "LENOX",
    "124": "CONSOLATION",
    "125": "HENLEY",
    "126": "PENITENCE",
    "129": "WELLESLEY",
    "130": "DORRNANCE",
    "133": "BLISS",
    "135": "LITCHFIELD",
    "137": "WOODLAND",
    "139": "SPANISH HYMN",
    "141": "HUBERT",
    "145": "WOODWORTH",
    "146": "FOUNTAIN",
    "148": "I BRING MY SINS TO THEE",
    "151": "RANKIN",
    "152": "BOYLSTON",
    "153": "SHAWMUT",
    "154": "ALETTA",
    "155": "SEYMOUR",
    "156": "OLIVE'S BROW",
    "157": "OLDEN",
    "158": "MANOAH",
    "159": "CONTRITION",
    "160": "MANOAH",
    "161": "ST. THOMAS",
    "162": "NAOMI",
    "163": "MERCY",
    "164": "WARE",
    "165": "HARVEY'S CHANT",
    "166": "MENDON",
    "167": "BALERMA",
    "168": "GALILEE",
    "169": "AVON",
    "170": "MOUNT VERNON",
    "171": "DORRNANCE",
    "172": "McCABE",
    "173": "TO-DAY",
    "176": "SELENA",
    "177": "MISSIONARY CHANT",
    "180": "WARD",
    "181": "DENNIS",
    "182": "EVAN",
    "183": "BEATITUDO",
    "184": "WELTON",
    "185": "MAITLAND",
    "187": "HOLLEY",
    "188": "LOWRY",
    "207": "\"There shall be showers of blessing:\"",
    "258": "CORONATION",
    "259": "MILES LANE",
    "260": "AMERICA",
    "261": "DIADEMATA",
    "262": "ARIEL",
    "265": "REGENT SQUARE",
    "267": "DIX",
    "268": "REGENT SQUARE",
    "269": "ANGEL VOICES",
    "271": "PAX TECUM",
    "277": "LELA",
    "279": "SUMNER",
    "281": "LAUDES DOMINI",
    "285": "SARUM",
    "287": "HATTIE",
    "295": "MORTON",
    "307": "BRADBURY",
    "309": "POSEN",
    "312": "CRUSADER",
    "314": "MARGARET",
    "317": "NORVAL",
    "318": "AURELIA",
    "319": "ANGEL'S STORY",
    "320": "WEBB",
    "321": "GREENLAND",
    "322": "MUNICH",
    "323": "LINNIE",
    "324": "ELLACOMBE",
    "325": "BERTHOLD",
    "326": "SAVOY CHAPEL",
    "327": "NICAEA",
    "328": "WORTHY",
    "329": "CREATION",
    "330": "VARINA",
    "331": "MATERNA",
    "332": "FRIEND",
    "333": "PARK STREET",
    "334": "RUSSIA",
    "335": "LYONS",
    "336": "BELOVED",
    "337": "RUTH",
    "338": "MARY MAGDALENE",
    "339": "CHAUTAUQUA",
    "340": "MONSELL",
    "341": "FABEN",
    "342": "HARWELL",
    "343": "ELLESIDE",
    "344": "CONTRAST",
    "345": "BEECHER",
    "346": "LOVE DIVINE",
    "348": "ST. LOUIS",
    "349": "DANKS",
    "350": "ST. CRISTOPHER",
    "351": "THANKSGIVING",
    "352": "MAIDSTONE",
    "353": "HERALD",
    "354": "AMBOY",
    "355": "ST. LEONARD",
    "359": "JERUSALEM",
    "360": "VOX DILECTI",
    "361": "ORTONVILLE",
    "369": "ARMAGEDDON",
    "370": "WALTHAM",
    "371": "UXBRIDGE",
    "372": "AZMON",
    "373": "GERMANY",
    "374": "SANKEY",
    "375": "DIX",
    "376": "SPANISH HYMN",
    "377": "FLEMMING",
    "378": "Praise ye the Lord; for it is good",
    "379": "NO SORROW",
    "380": "FREEPORT",
    "381": "PAX DEI",
    "382": "ELLERS",
    "384": "LATHBURY",
    "385": "ST. GEORGE'S, BOLTON",
    "386": "MENDEBRAS",
    "387": "LISCHER",
    "388": "SABBATH",
    "390": "CAROL",
    "391": "ITALY",
    "393": "GENEVA",
    "394": "CONVERT",
    "398": "NETTLETON",
    "401": "MARGARET",
    "402": "TIVERTON",
    "403": "DOMINUS REGIT ME",
    "404": "WAUGH",
    "405": "SILOAM",
    "406": "COATHAM",
    "408": "NASHVILLE",
    "410": "CHINA",
    "411": "FLEMMING",
    "412": "SERENITY",
    "413": "DENFIELD",
    "414": "BADEA",
    "415": "NEWELL",
    "416": "DENNIS",
    "417": "PEORIA",
    "418": "LUTON",
    "419": "BEATITUDO",
    "420": "GRATITUDE",
    "421": "SCHUMANN",
    "422": "WARE",
    "423": "MARLOW",
    "424": "ANGELS",
    "425": "HOLLEY",
    "426": "EDEN",
    "427": "MONKLAND",
    "428": "RAPHAEL",
    "429": "HURSLEY",
    "430": "HEBRON",
    "431": "PLEYEL",
    "432": "ELIZABETHTOWN",
    "433": "HERBERT",
    "434": "ST. JOHN'S",
    "435": "ZEPHYR",
    "436": "CHRISTMAS",
    "437": "NAOMI",
    "438": "SICILY",
    "439": "ROSE",
    "440": "HOPE",
    "441": "STOCKWELL",
    "442": "RATHBUN",
    "443": "VIENNA",
    "444": "AMES",
    "445": "SESSIONS",
    "446": "RATHBUN",
    "447": "LITCHFIELD",
    "448": "HOWARD",
    "449": "St. Agnes",
    "450": "CHRISTMAS",
    "451": "DUKE STREET",
    "452": "MIGDOL",
    "454": "RUSSIA",
    "455": "HARVEY'S CHANT",
    "456": "BURTON",
    "457": "WARREN",
    "458": "SERENITY",
    "459": "ST. CUTHBERT",
    "460": "GREENWOOD",
    "461": "SHINING SHORE",
    "462": "GREENVILLE",
    "463": "SPANISH HYMN",
    "468": "MOUNT OLIVE",
    "471": "ROCKINGHAM",
    "591": "STOCKWELL",
    "595": "ALMSGIVING",
    "603": "RUSSIAN HYMN",
    "618": "ST. SYLVESTER",
    "619": "AURELIA",
    "620": "RUTHERFORD",
    "621": "MIRIAM",
    "622": "LIFE'S HARVEST",
    "623": "ENDEAVOR",
    "624": "MISSIONARY HYMN",
    "625": "UNION SQUARE",
    "626": "CHENIES",
    "627": "CALEDONIA",
    "628": "ELLACOMBE",
    "629": "DRESDEN",
    "630": "JUNIOR ENDEAVOR",
    "631": "LUX BENIGNA",
    "632": "GUIDE",
    "633": "HOLLINGSIDE",
    "634": "REFUGE",
    "635": "MARTYN",
    "636": "DEERHURST",
    "637": "THE ALARM",
    "638": "NORTH",
    "639": "CHARITY",
    "640": "AUTUMN",
    "641": "FILLMORE",
    "642": "ONWARD",
    "643": "CONVERSE",
    "644": "TRUST",
    "645": "RUSSIAN HYMN",
    "646": "SALVATOR",
    "647": "Saviour, breathe an evening blessing",
    "648": "HUMILITY",
    "649": "BERTHOLD",
    "650": "I LOVE THEE",
    "651": "ANEW",
    "652": "GOULD",
    "653": "ELTHAM",
    "655": "EVENTIDE",
    "656": "ST. GERTRUDE",
    "657": "ST. GERTRUDE",
    "658": "ST. ALBAN",
    "659": "ST. GERTRUDE",
    "660": "JEWETT",
    "661": "ROTHMANN",
    "662": "DOANE",
    "663": "BETHANY",
    "664": "PORTUGUESE HYMN",
    "665": "GOSHEN",
    "668": "BARNES",
    "669": "WILLINGHAM",
    "670": "ITALIAN HYMN",
    "671": "FLEMMING",
    "675": "MELITA",
    "678": "ST. CATHERINE",
    "679": "RODMAN",
    "680": "MORNING LIGHT",
    "681": "EIN' FESTE BURG",
    "682": "AMSTERDAM",
    "687": "ROTHWELL",
    "689": "EL KADER",
    "692": "DAWNING",
    "693": "CUTLER",
    "694": "GABRIEL",
    "695": "CONSUMMATION",
    "697": "PROMISE",
    "698": "NEANDER",
    "700": "REGENT SQUARE",
    "705": "ZION",
    "709": "PENITENCE",
    "710": "MENDELSSOHN",
    "712": "SELVIN",
    "714": "EL KADER",
    "716": "WEBB",
    "720": "WORK",
    "721": "CHENIES",
    "722": "WORK",
    "723": "NORTHFIELD",
    "724": "EXHORTATION",
    "725": "DUNDEE",
    "727": "ST. ANNE",
    "729": "SHEPHERD",
    "731": "RIPLEY",
    "734": "DAWNING",
    "735": "GREENVILLE",
    "742": "SHINING SHORE",
    "743": "DENNIS",
    "744": "HEBRON",
    "745": "DAY",
    "746": "HERBERT",
    "747": "HART",
    "748": "SPOHR",
    "749": "\"INNOCENTS\"",
    "750": "BOYLSTON",
    "751": "OAKLAND",
    "752": "SILVER STREET",
    "753": "ZEPHYR",
    "754": "ST. THOMAS",
    "755": "MORNINGTON",
    "756": "CAPTIVITY",
    "757": "BLISS",
    "758": "NOTTING HILL",
    "759": "WARWICK",
    "760": "CRASSELIUS",
    "761": "HOLY CROSS",
    "762": "MASON",
    "763": "ST. MARTIN'S",
    "764": "HAMBURG",
    "765": "BELMONT",
    "766": "LAUREL HILL",
    "767": "BRADFORD",
    "768": "HORTON",
    "769": "BELMONT",
    "770": "ROOT",
    "771": "HEBER",
    "772": "GOLDEN",
    "773": "TRURO",
    "774": "VESPER",
    "775": "HURSLEY",
    "776": "MEAR",
    "777": "ROCKINGHAM",
    "778": "MALVERN",
    "779": "LORENZ",
    "780": "GERMANY",
    "781": "MELITA",
    "782": "MILLER",
    "783": "SHIRLEY",
    "784": "WILMOT",
    "785": "FLOWER",
    "786": "SILVERTON",
    "787": "SHIRLAND",
    "788": "LABAN",
    "789": "DUNDEE",
    "790": "OLD HUNDRED",
    "791": "MILES LANE",
    "792": "ZEPHYR",
    "793": "ARLINGTON",
    "794": "STEPHENS",
    "795": "ALL SAINTS",
    "796": "NUREMBERG",
    "797": "BERA",
    "798": "PATMOS",
    "799": "UXBRIDGE",
    "800": "COMMUNION",
    "801": "RETREAT",
    "802": "MERCY",
    "803": "GRANNIS",
    "804": "MT. VERNON",
    "805": "PALMER",
    "806": "FERN DELL",
    "807": "SEYMOUR",
    "808": "DOWNS",
    "809": "WINCHESTER",
    "810": "BROWN",
    "811": "CHOPIN",
    "812": "DENTON",
    "813": "COVENTRY",
    "814": "LOUVAN",
    "815": "RATHBUN",
    "816": "AMERICA",
    "817": "HAMBURG",
    "818": "DORT",
    "820": "WINTERBOURNE",
    "822": "WEBER",
    "823": "LAMBETH",
    "824": "TRUST",
    "825": "ERNAN",
    "826": "YORK",
    "827": "CADDO",
    "828": "UXBRIDGE",
    "829": "GREENWOOD",
    "830": "WOOLWICH",
    "831": "STOCKWELL",
    "832": "SPANISH HYMN",
    "833": "GERMANY",
    "834": "CANONBURY",
    "835": "ROOT",
    "836": "NOCTURN",
    "837": "DOVE",
    "840": "GUIDANCE",
    "841": "Lord, keep us safe this night",
    "842": "OAK",
    "843": "LAND OF REST",
    "844": "PERSEVERANCE",
    "846": "REST",
    "895": "ANTIOCH",
    "896": "ZERAH",
    "897": "PARADISE",
    "898": "EWING",
    "899": "VARINA",
    "900": "OAKLEY",
    "901": "WATCHMAN",
    "902": "CONTRAST",
    "906": "BONAR",
    "911": "AUSTRIA",
    "912": "NEANDER",
    "913": "DEERHURST",
    "915": "PILGRIMS",
    "916": "SHERWIN",
    "917": "ALFORD",
    "918": "ELLACOMBE",
    "920": "HAKES",
    "923": "ANVERN",
    "925": "ANDRE",
    "931": "BYRON",
    "932": "UNITY",
    "933": "AMERICA",
    "934": "TAMWORTH",
    "937": "HENDON",
    "938": "CHOPIN",
    "939": "PLEYEL",
    "940": "BOYLSTON",
    "941": "LAUREL HILL",
    "942": "ELLA",
    "945": "MERIBAH"
  },
  "unnamed": {
    "1": "What shall I do with Jesus?",
    "2": "White pages before us, thank God this is so",
    "3": "In the land of strangers",
    "4": "Drifting away from the Saviour",
    "5": "Some one will enter the pearly gate",
    "6": "There was One who was willing to die in my stead",
    "7": "Come, sinners, to the Living One",
    "8": "Jesus is tenderly calling thee home",
    "9": "O tender and sweet was the Father's voice",
    "10": "Like wand'ring sheep o'er mountains cold",
    "11": "There are two ways for trav'lers, only two ways",
    "12": "\"Whosoever heareth,\" shout, shout the sound!",
    "13": "\"Yet there is room!\"",
    "14": "Sound the alarm!  let the watchman cry",
    "15": "In darkness I lingered 'mid doubt and despair",
    "16": "O heart bowed down with sorrow!",
    "17": "I've wandered far away from God",
    "18": "Just one touch as He moves along",
    "19": "One thing I of the Lord desire",
    "20": "Christ is knocking at my sad heart",
    "21": "There's a Stranger at the door",
    "22": "If you could see Christ standing here tonight",
    "23": "I cannot drive the nails again",
    "24": "Sing it o'er and o'er again",
    "25": "If you are tired of the load of your sin",
    "26": "A ruler once came to Jesus by night",
    "27": "Would you be free from your burden of sin?",
    "28": "Blessed be the Fountain of blood",
    "29": "Ring the bells of heaven!  there is joy today",
    "30": "Able to deliver!  sound it far and near",
    "31": "O hear my cry, be gracious now to me",
    "32": "We'll build on the Rock, the living Rock",
    "33": "We are building in sorrow or joy",
    "34": "We tell it as we journey t'ward the mansions built above",
    "35": "Knocking, knocking, who is there?",
    "36": "'Twas in the days of careless youth, when life was fair and bright",
    "37": "\"Eternity!  where?\"  It floats in the air",
    "38": "The day is dead, and Egypt's night returning",
    "39": "In the silent midnight watches",
    "40": "Tell me the story of Jesus",
    "41": "O who is this that cometh",
    "42": "When Jesus shall gather the nations",
    "43": "Called to the feast by the King are we",
    "44": "There's room for you to anchor",
    "45": "While Jesus whispers to you",
    "46": "Jesus, the loving Shepherd",
    "47": "Not in the hour of death",
    "48": "At the feast of Belshazzar and a thousand of his lords",
    "49": "When the Judge shall weigh our motives",
    "50": "Oh, the best friend to have is Jesus",
    "51": "All to Jesus I surrender",
    "52": "What means this eager, anxious throng",
    "53": "I have a Saviour, he's pleading in glory",
    "54": "Are you tenting on the lowlands",
    "55": "Hear the words our Saviour hath spoken",
    "56": "Sowing the seed by the daylight fair",
    "57": "There's not a friend like the lowly Jesus",
    "58": "Would you live for Jesus, and be always pure and good?",
    "59": "Who is on the Lord's side?",
    "60": "Only a step to Jesus!",
    "61": "There were ninety and nine that safely lay",
    "62": "What will you do with the King called Jesus?",
    "63": "My blessed Lord was crucified",
    "64": "Lord Jesus, I long to be perfectly whole",
    "65": "There's life in a look at the sacred cross",
    "66": "Yield not to temptation",
    "67": "Dare to do right, dare to be true!",
    "68": "I think when I read that sweet story of old",
    "69": "Why labor for treasures that rust and decay",
    "71": "I will early seek the Saviour",
    "72": "Who'll be the next to follow Jesus?",
    "73": "Now just a word for Jesus",
    "74": "Sing them over again to me",
    "75": "Jesus, my Saviour, to Bethlehem came",
    "76": "Softly and tenderly Jesus is calling",
    "77": "Like as a father pities his child",
    "78": "We have heard a joyful sound",
    "79": "Tho' your sins be as scarlet",
    "80": "Look upon Jesus, sinless is He",
    "81": "While we pray and while we plead",
    "82": "Behold, behold the Lamb of God",
    "83": "By faith I view my Saviour dying",
    "84": "The mistakes of my life are many",
    "85": "There is no love like the love of Jesus",
    "86": "There's a great day coming",
    "87": "Pass me not, O gentle Saviour",
    "88": "Have you been to Jesus for the cleansing pow'r?",
    "89": "Almost persuaded now to believe",
    "90": "I stood outside the gate",
    "91": "There is a gate that stands ajar",
    "92": "Weeping will not save me",
    "93": "What can wash away my sin?",
    "94": "The great Physician now is near",
    "95": "Come, ev'ry soul by sin oppressed",
    "96": "I gave my life for Thee",
    "97": "Not saved are we by trying",
    "98": "Where is my wand'ring boy to-night",
    "99": "Refining fire, go thro' my heart",
    "100": "Crowded is your heart with cares",
    "101": "I hear thy welcome voice",
    "102": "I was once far away from the Saviour",
    "103": "Jesus, my Lord, to thee I cry",
    "107": "I hear the Saviour say",
    "109": "I am coming to the cross",
    "110": "O now I see the crimson wave",
    "127": "The great decisive day is at hand",
    "128": "There's a wideness in God's mercy",
    "131": "Nothing but leaves!  The Spirit grieves",
    "132": "Heaven is not far away",
    "134": "Baptize us anew",
    "136": "The last call of mercy now lingers for thee",
    "147": "Flee as a bird to your mountain",
    "149": "O spotless Lamb!  I come to thee",
    "150": "Alas!  and did my Saviour bleed?",
    "174": "Lord, I hear of show'rs of blessing",
    "175": "There are angels hov'ring round",
    "178": "Come, ye sinners, poor and needy",
    "179": "Come to Jesus, Come to Jesus",
    "186": "Father, I stretch my hand to thee",
    "189": "They bro't their gifts to Jesus",
    "190": "Hallelujahs to Jesus!",
    "191": "To God be the glory, great things He hath done",
    "192": "My heart was distress'd 'neath Jehovah's dread frown",
    "193": "O, spread the tidings round",
    "194": "I will sing of Jesus' love",
    "195": "Would we be joyful in the Lord?",
    "196": "Be silent, be silent",
    "197": "Come out in the sunshine!",
    "198": "There's sunshine in my soul to-day",
    "199": "Redeemed!  how I love to proclaim it!",
    "200": "I can hear my Saviour calling",
    "201": "He will mention them no more forever",
    "202": "Nearer, still nearer, close to Thy heart",
    "203": "I once was in the desert, all weary, sad and lone",
    "204": "Christ has for sin atonement made",
    "205": "Blessed assurance, Jesus is mine!",
    "206": "We'll tarry by the living waters",
    "208": "There comes to my heart one sweet strain",
    "209": "The dove of peace sings in my heart",
    "210": "Far away in the depths of my spirit tonight",
    "211": "My soul in sad exile was out on life's sea",
    "212": "Alas!  and did my Saviour bleed",
    "213": "The cross!  it standeth fast",
    "214": "Awake, my soul, and greet the dawn",
    "215": "The name of Jesus is so sweet",
    "216": "Take the name of Jesus with you",
    "217": "Dearest name in earth or heaven",
    "218": "O, the bitter pain and sorrow",
    "219": "Standing on the promises of Christ my King",
    "220": "O worship the Lord in the beauty of holiness",
    "221": "Sav'd to the uttermost:  I am the Lord's",
    "222": "Safe in the arms of Jesus",
    "223": "Nor silver nor gold hath obtained my redemption",
    "224": "Since Christ my soul from sin set free",
    "225": "Tho' my sins were once like crimson red",
    "226": "Praise Him!  praise Him!  Jesus, our blessed Redeemer!",
    "227": "Wake the song of joy and gladness",
    "228": "O come, let us sing unto the Lord",
    "229": "There is sunlight on the hilltop",
    "230": "Not I but Christ, be honored, loved, exalted",
    "231": "My heart's a tuneful harp when Christ abides within",
    "232": "I feel like singing all the time",
    "233": "Jesus comes with pow'r to gladden",
    "234": "O Jesus my Redeemer",
    "235": "O sing unto the Lord a new song",
    "236": "I have a song I love to sing",
    "237": "I sing the love of God, my Father",
    "238": "One there is above all others",
    "239": "Hear the words of Scripture from the ages past",
    "240": "Oh, bliss of the purified!  bliss of the free!",
    "241": "\"Called unto holiness,\" Church of our God",
    "242": "A beautiful star there rose one night",
    "243": "There's a dark and a troubled side of life",
    "244": "\"Peace upon earth!\" the angels sang",
    "245": "In joyful high and holy lays",
    "246": "I've found a friend in Jesus, He's ev'rything to me",
    "247": "Each cooing dove and sighing bough",
    "248": "Long ago the children sang a song",
    "249": "Do you know what the dewdrops say",
    "250": "Don't forget the Sabbath",
    "251": "I've two little hands to work for Jesus",
    "252": "God sees the little sparrow fall",
    "253": "Little stars that twinkle in the heaven's blue",
    "254": "Jesus, I will follow thee",
    "255": "Sweetly sing, sweetly sing",
    "256": "Our sweetest songs of gladness",
    "257": "All hail the power of Jesus' name",
    "263": "Come, children, hail the Prince of Peace",
    "264": "We are children of a King",
    "270": "'Tis the blessed hour of prayer, when our hearts lowly bend",
    "272": "List to the chime, 'tis meeting time",
    "273": "Children singing, sweet bells ringing!",
    "274": "Strains of music often greet me",
    "275": "Valley lilies, meek and lowly",
    "276": "I wandered in the shades of night",
    "278": "Jesus, Thou hast promised",
    "280": "Welcome!  thrice welcome!",
    "282": "I am Thine, O Lord, I have heard Thy voice",
    "283": "Jesus loves me!  this I know",
    "284": "Let our hearts be always cheerful",
    "286": "More like Jesus would I be",
    "288": "O for a thousand tongues to sing",
    "289": "Jesus, keep me near the cross",
    "290": "Since on my Saviour I believed",
    "292": "I have entered the valley of blessing so sweet",
    "293": "In the blood from the cross",
    "294": "My hope is built on nothing less",
    "296": "Walking with thee, my God",
    "297": "More love to thee",
    "298": "O bliss of the pure ones!",
    "299": "My Jesus, I love thee",
    "300": "Down at the cross where my Saviour died",
    "301": "I know I love thee better, Lord",
    "302": "There's no other name like Jesus",
    "303": "Have I need of aught, O Saviour!",
    "304": "God loved the world of sinners lost",
    "305": "Where He may lead me I will go",
    "306": "Fade, fade each earthly joy",
    "308": "Hover o'er me, Holy Spirit",
    "310": "All for Jesus, all for Jesus!",
    "311": "Tell me the old, old story",
    "313": "Hark!  the herald angels sing",
    "315": "Take the world, but give me Jesus",
    "316": "Take my life, and let it be",
    "347": "Fresh from the throne of glory",
    "366": "Joys are flowing like a river",
    "367": "Awake, my soul, to joyful lays",
    "383": "My life, my love, I give to thee",
    "395": "I would be, dear Saviour, wholly thine",
    "396": "We praise thee, O God, for the Son of thy love",
    "399": "O happy day!  that fixed my choice",
    "400": "There is no name so sweet on earth",
    "409": "I will follow thee, my Saviour",
    "453": "Sing of Jesus, sing forever",
    "464": "O give thanks unto the Lord, for He is good",
    "465": "Glory be to the Father",
    "466": "Glory be to the Father",
    "467": "Glory be to the Father",
    "469": "Our Father which art in heaven",
    "470": "Praise God, from whom all blessings flow",
    "472": "All things come of Thee, O Lord",
    "473": "Around the world the chorus rings",
    "474": "Saved to serve in any station",
    "475": "A year of precious blessings",
    "476": "I love to tell the story",
    "477": "Working, O Christ, with thee",
    "478": "Just to trust in the Lord, just to lean on His Word",
    "479": "Rescue the perishing",
    "480": "Brightly beams our Father's mercy",
    "481": "Are you Christ's light bearer?",
    "482": "An open Bible for the world!",
    "483": "God bids his people on the earth",
    "484": "Loyalty to the Master, loyalty to the King",
    "485": "Take time to be holy",
    "486": "There are lonely hearts to cherish",
    "487": "I cease to sing of sweet tomorrow",
    "488": "Conquering now and still to conquer",
    "489": "I'm pressing on the upward way",
    "490": "Encamped along the hills of light",
    "491": "Saviour, more than life to me",
    "492": "Does Jesus care when my heart is pain'd",
    "493": "O blessed rest, when we recline",
    "494": "The cross that he gave may be heavy",
    "495": "When we walk with the Lord",
    "496": "Dying with Jesus, by death reckoned mine",
    "497": "Moment by moment, hour by hour",
    "498": "Give me the Bible, star of gladness gleaming",
    "499": "Not a wasted moment in the morning fair",
    "500": "O softly the Spirit is whisp'ring to me",
    "501": "Jesus bids us shine with a pure, clear light",
    "502": "Just lean upon the arms of Jesus",
    "503": "What a fellowship, what a joy divine",
    "504": "God be with you till we meet again",
    "505": "The Lord's our Rock, in him we hide",
    "506": "O safe to the Rock that is higher than I",
    "507": "Under His wings I am safely abiding",
    "508": "O Christian, awake!  'tis the Master's command",
    "509": "Firmly stand for God, in the world's mad strife",
    "510": "Sound the battle cry",
    "511": "Strike!  O strike for vict'ry",
    "512": "Who will volunteer?",
    "513": "Ask not to be excused",
    "514": "My Father is rich in houses and lands",
    "515": "Are you weary, are you heavy hearted?",
    "516": "When peace like a river attendeth my way",
    "517": "In heav'nly love abiding",
    "518": "As of old when the hosts of Israel",
    "519": "'Tis so sweet to trust in Jesus",
    "520": "Lift him up, 'tis he that bids you",
    "521": "Look upon the golden image",
    "522": "Is there anyone can help us, one who understands our hearts",
    "523": "Look for the beautiful, look for the true",
    "524": "Are you heavy laden and with sorrow tried?",
    "525": "More about Jesus I would know",
    "526": "Father, we come to thee",
    "527": "Saviour, lead me lest I stray",
    "528": "The Lord is my light",
    "529": "The angel of the Lord encampeth",
    "530": "Christ, our mighty Captain, leads against the foe",
    "531": "In the highways and hedges go seek for the lost",
    "532": "Seeking the lost, yes, kindly entreating",
    "533": "Would you win a Saviour's blessing?",
    "534": "Closer to thee, my Father, draw me",
    "535": "Anywhere with Jesus I can safely go",
    "536": "Be with us, Lord, as forth we go",
    "537": "Go ye into all the world",
    "538": "Life is not a cloudless journey",
    "540": "Walk in the light the Lord has given",
    "541": "I must have the Saviour with me",
    "542": "What are you doing for Jesus",
    "543": "When the cross seems hard to carry",
    "544": "Throw out the Life-Line across the dark wave",
    "545": "Out upon an angry ocean",
    "546": "On the shore beyond the sea",
    "547": "Far and near the fields are teeming",
    "548": "O where are the reapers that garner in",
    "549": "One more day's work for Jesus",
    "550": "Pray for the erring ones, faith shall reclaim them",
    "551": "The home where changes never come",
    "552": "I am thinking today of that beautiful land",
    "553": "All my class!  not one forgotten",
    "554": "Speak to my soul, dear Jesus",
    "555": "Watch, for the time is short",
    "556": "When softly fades the dying day",
    "557": "Lonely?  no, not lonely",
    "558": "Lifetime is working time, spend no idle days",
    "559": "If any little word of mine",
    "560": "Never be sad or desponding",
    "561": "Hark!  'tis the Shepherd's voice I hear",
    "562": "I have learn'd the wondrous secret",
    "563": "Lord, for tomorrow and its needs",
    "564": "Will your anchor hold in the storm of life",
    "565": "Christian, onward!  Christ is coming",
    "566": "It may not be on the mountain's height",
    "567": "'Tis love that makes us happy",
    "568": "Let us gather up the sunbeams",
    "569": "I wash'd my hands this morning",
    "570": "If your hand's on the plow, hold on, hold on",
    "571": "Master, hast thou work for me?",
    "572": "In the struggle of life there's a conquest to win",
    "573": "Hear the pennies dropping!",
    "574": "Gladly, gladly, toiling for the Master",
    "575": "Give!  said the golden sun",
    "576": "To the work!  to the work!  we are servants of God",
    "577": "Beautiful the little hands",
    "578": "We should be like gardens",
    "579": "If I were a sunbeam",
    "580": "There is beauty all around",
    "581": "Angry words!  oh, let them never",
    "582": "Into the tent where a gypsy boy lay",
    "583": "Sowing in the morning, sowing seeds of kindness",
    "584": "Master, the tempest is raging!",
    "585": "Cold water is the cup that cheers",
    "586": "Look for the way-marks as you journey on",
    "587": "Hear the temp'rance call",
    "588": "He that goeth forth with weeping",
    "589": "The world's glorious harvest is fast drawing on",
    "590": "Man the life-boat!  Man the life-boat!",
    "592": "Out from the campfire's red glowing",
    "593": "Now to heav'n our pray'r ascending",
    "594": "Give of your best to the Master",
    "596": "Buy up the opportunity",
    "597": "Blessed Lord, how much I need thee!",
    "598": "Oh, to be \"Kept for Jesus!\"",
    "600": "Ready to suffer grief or pain",
    "601": "Precious promise God hath given",
    "602": "Forward, brothers, forward!",
    "604": "More diligence give me",
    "606": "Not now, my child, a little more rough tossing",
    "607": "Let us work for the school with our hearts and our hands",
    "608": "Sweet Sabbath School!  more dear to me",
    "609": "I need Thee every hour",
    "610": "I am passing down the valley that they say is so lone",
    "611": "All the way my Saviour leads me",
    "612": "When morning lights the eastern skies",
    "613": "O sometimes the shadows are deep",
    "614": "Saviour!  Thy dying love",
    "615": "What tho' clouds are hov'ring o'er me",
    "616": "\"Call them in\", the poor, the wretched",
    "617": "There's a cry from Macedonia  Come and help us",
    "654": "Rock of Ages, cleft for me!",
    "666": "The Lord is my Shepherd, no want shall I know",
    "667": "Tho' faint, yet pursuing, we go on our way",
    "672": "Master, no offering",
    "673": "Answer the call, ye brave men",
    "677": "He leadeth me!  O blessed tho't!",
    "683": "Watchman, blow the gospel trumpet",
    "684": "Words of cheer from the battlefield of life",
    "685": "Cast thy burden on the Lord",
    "686": "We lay us calmly down to sleep",
    "691": "I've reach'd the land of corn and wine",
    "696": "Go forth on wings of faith and pray'r",
    "701": "Anywhere, dear Saviour",
    "702": "In some way or other the Lord will provide",
    "703": "Speed away!  speed away! over mountain and sea",
    "704": "Could you wait, could you wait if a brother were lost",
    "737": "Mid scenes of confusion and creature complaints",
    "739": "Kind words can never die",
    "740": "Out on an ocean all boundless we ride",
    "741": "Sweet hour of pray'r, sweet hour of pray'r",
    "819": "The Lord worketh, let us work too",
    "821": "For Jesus, all my morning hours",
    "845": "How far from home?  I asked, as on",
    "848": "We shall meet beyond the river",
    "849": "When my life work is ended, and I cross the swelling tide",
    "850": "Beautiful valley of Eden",
    "851": "Above the clouds that veil the blue",
    "852": "When He cometh, when he cometh",
    "853": "Down life's dark vale we wander",
    "854": "There'll be no dark valley when Jesus comes",
    "855": "The Homeland!  O the Homeland!",
    "856": "We shall reach the summer land",
    "857": "Our Lord is now rejected",
    "858": "Light after darkness",
    "859": "When we lay our burdens down",
    "860": "Lord, I care not for riches",
    "861": "Face to face with Christ my Saviour",
    "862": "In the land of fadeless day",
    "863": "O there'll be joy when the work is done",
    "864": "In the glad time of the harvest",
    "865": "When the trumpet of the Lord shall sound, and time shall be no more",
    "866": "With friends on earth we meet in gladness",
    "867": "It may be at morn, when the day is awaking",
    "868": "Are you ready for the Bridegroom",
    "869": "We shall walk with him in white",
    "870": "\"We would see Jesus;\" for the shadows lengthen",
    "871": "Who are these whose songs are sounding",
    "872": "We shall meet beyond the skies",
    "873": "Breaking thro' the clouds that gather",
    "874": "Sorrow and care may meet",
    "875": "Soul amid earth sorrows dwelling",
    "876": "When I shall awake in that fair morn of morns",
    "877": "Watch, ye saints, with eyelids waking",
    "878": "We know not the hour of the Master's appearing",
    "879": "There's a land that is fairer than day",
    "880": "Oh, glory to God!  it is coming again",
    "881": "I am waiting for the morning",
    "882": "One sweetly solemn tho't",
    "883": "There is a land mine eye hath seen",
    "884": "Some day the silver cord will break",
    "885": "We know not the time when He cometh",
    "886": "When thou comest in Thy kingdom",
    "887": "Come, we that love the Lord",
    "888": "Beautiful city, haven of peace",
    "889": "Angel voices sweetly singing",
    "890": "Who, who are these beyond the chilly wave",
    "891": "When we hear the music ringing",
    "892": "The golden morning is fast approaching",
    "893": "When the mists have rolled in splendor",
    "894": "Sweet promise is giv'n to all who believe",
    "903": "Hail to the brightness of Zion's glad morning!",
    "904": "Daughter of Zion, awake from thy sadness",
    "905": "On Jordan's stormy banks I stand",
    "907": "Shall we gather at the river",
    "908": "\"Forever with the Lord!\"",
    "909": "We have joyously voyaging over the main",
    "910": "\"Land ahead!\"  its fruits are waving",
    "914": "How sweet are the tidings that greet the pilgrim's ear",
    "919": "I will sing you a song of that beautiful land",
    "921": "Shall we meet beyond the river",
    "922": "When Jesus calls His jewels",
    "927": "When I can read my title clear",
    "928": "In the Christian's home in glory",
    "929": "Lift up the trumpet, and loud let it ring",
    "930": "The coming King is at the door",
    "943": "There'll be no grief in heav'n",
    "944": "Meet again when time is o'er",
    "946": "O how I long to see that day",
    "947": "My rest is in heaven, my rest is not here",
    "948": "I'm weary.  I'm fainting; my day's work is done",
    "949": "No tears in yonder home",
    "951": "Lord, have mercy, have mercy upon us"
  }
}